5f8b22f5f815a3776376__mypyc.cpython-39-x86_64-linux-gnu.so
909239aaf4f10b4a0b69__mypyc.cpython-39-x86_64-linux-gnu.so
faster_ens/__init__.cpython-39-x86_64-linux-gnu.so
faster_ens/__init__.py
faster_ens/_normalization.cpython-39-x86_64-linux-gnu.so
faster_ens/_normalization.py
faster_ens/abis.cpython-39-x86_64-linux-gnu.so
faster_ens/abis.py
faster_ens/abis__mypyc.cpython-39-x86_64-linux-gnu.so
faster_ens/async_ens.py
faster_ens/auto.cpython-39-x86_64-linux-gnu.so
faster_ens/auto.py
faster_ens/base_ens.cpython-39-x86_64-linux-gnu.so
faster_ens/base_ens.py
faster_ens/constants.cpython-39-x86_64-linux-gnu.so
faster_ens/constants.py
faster_ens/contract_data.cpython-39-x86_64-linux-gnu.so
faster_ens/contract_data.py
faster_ens/contract_data__mypyc.cpython-39-x86_64-linux-gnu.so
faster_ens/ens.py
faster_ens/exceptions.cpython-39-x86_64-linux-gnu.so
faster_ens/exceptions.py
faster_ens/py.typed
faster_ens/utils.cpython-39-x86_64-linux-gnu.so
faster_ens/utils.py
faster_ens/specs/nf.json
faster_ens/specs/normalization_spec.json
faster_web3/__init__.py
faster_web3/constants.cpython-39-x86_64-linux-gnu.so
faster_web3/constants.py
faster_web3/datastructures.py
faster_web3/exceptions.py
faster_web3/geth.py
faster_web3/logs.py
faster_web3/main.py
faster_web3/manager.py
faster_web3/method.py
faster_web3/module.py
faster_web3/net.py
faster_web3/py.typed
faster_web3/testing.py
faster_web3/tracing.py
faster_web3/types.cpython-39-x86_64-linux-gnu.so
faster_web3/types.py
faster_web3/_utils/__init__.py
faster_web3/_utils/abi.py
faster_web3/_utils/abi_element_identifiers.py
faster_web3/_utils/async_caching.py
faster_web3/_utils/async_transactions.cpython-39-x86_64-linux-gnu.so
faster_web3/_utils/async_transactions.py
faster_web3/_utils/batching.cpython-39-x86_64-linux-gnu.so
faster_web3/_utils/batching.py
faster_web3/_utils/blocks.cpython-39-x86_64-linux-gnu.so
faster_web3/_utils/blocks.py
faster_web3-7.14.0.dist-info/METADATA
faster_web3-7.14.0.dist-info/WHEEL
faster_web3-7.14.0.dist-info/top_level.txt
faster_web3-7.14.0.dist-info/RECORD
faster_web3-7.14.0.dist-info/licenses/LICENSE
