Metadata-Version: 2.1
Name: faster_web3
Version: 7.14.0
Summary: A faster fork of web3: A Python library for interacting with Ethereum. Implemented in C.
Home-page: https://github.com/BobTheBuidler/faster-web3.py
Author: The Ethereum Foundation
Author-email: snakecharmers@ethereum.org
License: MIT
Project-URL: Documentation, https://web3py.readthedocs.io/en/stable/
Project-URL: Release Notes, https://github.com/BobTheBuidler/faster-web3.py/releases
Project-URL: Issues, https://github.com/BobTheBuidler/faster-web3.py/issues
Project-URL: Source, https://github.com/BobTheBuidler/faster-web3.py
Project-URL: Original, https://github.com/ethereum/web3.py
Keywords: ethereum
Classifier: Development Status :: 5 - Production/Stable
Classifier: Intended Audience :: Developers
Classifier: License :: OSI Approved :: MIT License
Classifier: Natural Language :: English
Classifier: Programming Language :: Python :: 3
Classifier: Programming Language :: Python :: 3.9
Classifier: Programming Language :: Python :: 3.10
Classifier: Programming Language :: Python :: 3.11
Classifier: Programming Language :: Python :: 3.12
Classifier: Programming Language :: Python :: 3.13
Classifier: Programming Language :: Python :: 3.14
Requires-Python: >=3.9, <4
Provides-Extra: tester
Provides-Extra: dev
Provides-Extra: docs
Provides-Extra: test
License-File: LICENSE
